dbrownell_Placeholder/UvScaffolding_sample_file.py
dbrownell_Placeholder/__init__.py
dbrownell_Placeholder/py.typed
dbrownell_placeholder-0.1.4.dist-info/WHEEL
dbrownell_placeholder-0.1.4.dist-info/METADATA
dbrownell_placeholder-0.1.4.dist-info/RECORD
