Metadata-Version: 2.3
Name: dbrownell-placeholder
Version: 0.1.4
Summary: Placeholder repository where I work on code before it is moved to a more permanent location. I can't think of a good reason why anyone else would want to use this repository.
Author: David Brownell
Author-email: David Brownell <github@DavidBrownell.com>
License: MIT
Classifier: Operating System :: MacOS
Classifier: Operating System :: Microsoft :: Windows
Classifier: Operating System :: POSIX :: Linux
Classifier: Programming Language :: Python
Classifier: Programming Language :: Python :: 3.13
Classifier: Programming Language :: Python :: 3.12
Classifier: Programming Language :: Python :: 3.11
Classifier: Programming Language :: Python :: 3.10
Requires-Python: >=3.10
Project-URL: Documentation, https://github.com/davidbrownell/dbrownell_Placeholder
Project-URL: Homepage, https://github.com/davidbrownell/dbrownell_Placeholder
Project-URL: Repository, https://github.com/davidbrownell/dbrownell_Placeholder
